treehouse.cpython-39-darwin.so
treehouse-0.2.0.dist-info/LICENSE
treehouse-0.2.0.dist-info/METADATA
treehouse-0.2.0.dist-info/WHEEL
treehouse-0.2.0.dist-info/top_level.txt
treehouse-0.2.0.dist-info/RECORD
